fm_zoo/__init__.py
fm_zoo/afi.py
fm_zoo/afm.py
fm_zoo/common.py
fm_zoo/dfm.py
fm_zoo/ffm.py
fm_zoo/fm.py
fm_zoo/fnfm.py
fm_zoo/fnn.py
fm_zoo/nfm.py
fm_zoo/xdfm.py
tf2_fm_zoo-0.1.1.dist-info/LICENSE
tf2_fm_zoo-0.1.1.dist-info/METADATA
tf2_fm_zoo-0.1.1.dist-info/WHEEL
tf2_fm_zoo-0.1.1.dist-info/top_level.txt
tf2_fm_zoo-0.1.1.dist-info/RECORD
