Metadata-Version: 2.1
Name: tf2-fm-zoo
Version: 0.1.1
Summary: UNKNOWN
Home-page: https://github.com/RoetGer/tf2-fm-zoo
License: UNKNOWN
Platform: UNKNOWN
